UAVReaders.cpython-310-i386-linux-gnu.so
uavreaders.libs/libgcc_s-887de51c.so.1
uavreaders.libs/libstdc++-d6415257.so.6.0.33
uavreaders-1.0.6.dist-info/METADATA
uavreaders-1.0.6.dist-info/WHEEL
uavreaders-1.0.6.dist-info/top_level.txt
uavreaders-1.0.6.dist-info/RECORD
uavreaders-1.0.6.dist-info/licenses/LICENSE
