Metadata-Version: 2.1
Name: UAVReaders
Version: 1.0.6
Summary: Parsers for UAV/Aerial Drone-related formats like MavLink and DataFlash
Author: Christian Clifford
Author-email: Christian Clifford <cjclifford@alaska.edu>
Requires-Python: >=3.8
License-File: LICENSE
